venvmngr/__init__.py
venvmngr/__main__.py
venvmngr/_base.py
venvmngr/_pypi.py
venvmngr/_uv.py
venvmngr/_venv.py
venvmngr/utils.py
venvmngr-0.2.0.dist-info/METADATA
venvmngr-0.2.0.dist-info/WHEEL
venvmngr-0.2.0.dist-info/entry_points.txt
venvmngr-0.2.0.dist-info/licenses/LICENCE
venvmngr-0.2.0.dist-info/RECORD
