Metadata-Version: 2.4
Name: venvmngr
Version: 0.2.0
Summary: managing a local environment
Author-email: JulianKimmig <julian.kimmig@gmx.net>
License: MIT License
License-File: LICENCE
Requires-Python: >=3.9
Requires-Dist: packaging
Requires-Dist: psutil>=2.0.0
Requires-Dist: requests
Requires-Dist: subprocess-monitor>=0.2.0
Requires-Dist: uv>=0.5.21
Provides-Extra: dev
Requires-Dist: mypy; extra == 'dev'
Requires-Dist: pre-commit>=4.3.0; extra == 'dev'
Requires-Dist: pytest; extra == 'dev'
Requires-Dist: pytest-asyncio; extra == 'dev'
Requires-Dist: pytest-cov; extra == 'dev'
Requires-Dist: ruff; extra == 'dev'
